MANIFEST.in
README.rst
setup.cfg
setup.py
docs/HISTORY.txt
docs/INSTALL.txt
docs/LICENSE.GPL
docs/LICENSE.txt
seantis/__init__.py
seantis.dir.contacts.egg-info/PKG-INFO
seantis.dir.contacts.egg-info/SOURCES.txt
seantis.dir.contacts.egg-info/dependency_links.txt
seantis.dir.contacts.egg-info/entry_points.txt
seantis.dir.contacts.egg-info/namespace_packages.txt
seantis.dir.contacts.egg-info/not-zip-safe
seantis.dir.contacts.egg-info/requires.txt
seantis.dir.contacts.egg-info/top_level.txt
seantis/dir/__init__.py
seantis/dir/contacts/__init__.py
seantis/dir/contacts/configure.zcml
seantis/dir/contacts/contact.py
seantis/dir/contacts/directory.py
seantis/dir/contacts/item.py
seantis/dir/contacts/sync.sh
seantis/dir/contacts/testing.py
seantis/dir/contacts/upgrades.py
seantis/dir/contacts/locales/seantis.dir.contacts.pot
seantis/dir/contacts/locales/de/LC_MESSAGES/seantis.dir.contacts.po
seantis/dir/contacts/profiles/default/cssregistry.xml
seantis/dir/contacts/profiles/default/metadata.xml
seantis/dir/contacts/profiles/default/types.xml
seantis/dir/contacts/profiles/default/types/seantis.dir.contacts.contact.xml
seantis/dir/contacts/profiles/default/types/seantis.dir.contacts.directory.xml
seantis/dir/contacts/profiles/default/types/seantis.dir.contacts.item.xml
seantis/dir/contacts/resources/seantis-dir-contacts.css
seantis/dir/contacts/templates/directory.pt
seantis/dir/contacts/templates/directorydetail.pt
seantis/dir/contacts/templates/item.pt
seantis/dir/contacts/tests/__init__.py
seantis/dir/contacts/tests/test_contact.py