Metadata-Version: 1.1
Name: seantis.dir.contacts
Version: 1.8
Summary: Directory of Contacts
Home-page: https://github.com/seantis/seantis.dir.contacts
Author: Seantis GmbH
Author-email: info@seantis.ch
License: GPL v2
Platform: UNKNOWN
Classifier: Framework :: Plone
Classifier: Framework :: Plone :: 4.3
Classifier: Intended Audience :: Developers
Classifier: Topic :: Software Development :: Libraries :: Python Modules
Classifier: Programming Language :: Python
